zaber_motion_bindings_windows/__init__.py
zaber_motion_bindings_windows/bindings.py
zaber_motion_bindings_windows/version.py
zaber_motion_bindings_windows/zaber-motion-lib-windows-386.dll
zaber_motion_bindings_windows/zaber-motion-lib-windows-amd64.dll
zaber_motion_bindings_windows-5.1.1.dist-info/LICENSE.txt
zaber_motion_bindings_windows-5.1.1.dist-info/METADATA
zaber_motion_bindings_windows-5.1.1.dist-info/WHEEL
zaber_motion_bindings_windows-5.1.1.dist-info/top_level.txt
zaber_motion_bindings_windows-5.1.1.dist-info/RECORD
